blockstream/__init__.py
blockstream/blockexplorer.py
blockstream/cli.py
blockstream/util.py
blockstream-0.3.0.dist-info/LICENSE
blockstream-0.3.0.dist-info/METADATA
blockstream-0.3.0.dist-info/WHEEL
blockstream-0.3.0.dist-info/entry_points.txt
blockstream-0.3.0.dist-info/top_level.txt
blockstream-0.3.0.dist-info/RECORD
