Metadata-Version: 2.1
Name: blockstream
Version: 0.3.0
Summary: API wrapper and CLI for blockstream block explorer
Home-page: http://github.com/psqnt/blockstream
Author: psqnt
License: MIT
Platform: UNKNOWN
Requires-Python: >=3
Requires-Dist: requests
Requires-Dist: Click
